eeyore/__init__.py
eeyore/eeyore.py
eeyore/chains/__init__.py
eeyore/chains/chain.py
eeyore/chains/chain_file.py
eeyore/chains/chain_list.py
eeyore/chains/chain_lists.py
eeyore/constants/__init__.py
eeyore/constants/constants.py
eeyore/data/__init__.py
eeyore/data/banknotes/__init__.py
eeyore/data/banknotes/readme.md
eeyore/data/banknotes/x.csv
eeyore/data/banknotes/y.csv
eeyore/data/iris/__init__.py
eeyore/data/iris/readme.md
eeyore/data/iris/x.csv
eeyore/data/iris/y.csv
eeyore/data/xor/__init__.py
eeyore/data/xor/x.csv
eeyore/data/xor/y.csv
eeyore/datasets/__init__.py
eeyore/datasets/data_counter.py
eeyore/datasets/data_info.py
eeyore/datasets/empty_dataset.py
eeyore/datasets/idataset.py
eeyore/datasets/mld_batcher.py
eeyore/datasets/mld_classification_batcher.py
eeyore/datasets/xydataset.py
eeyore/datasets/xyidataset.py
eeyore/integrators/__init__.py
eeyore/integrators/integrator.py
eeyore/integrators/mcintegrator.py
eeyore/itertools/__init__.py
eeyore/itertools/chunk_evenly.py
eeyore/kernels/__init__.py
eeyore/kernels/demc_kernel.py
eeyore/kernels/homogeneous_kernel.py
eeyore/kernels/iso_se_kernel.py
eeyore/kernels/kernel.py
eeyore/kernels/multivariate_normal_kernel.py
eeyore/kernels/normal_kernel.py
eeyore/kernels/normalized_kernel.py
eeyore/kernels/periodic_kernel.py
eeyore/kernels/rq_kernel.py
eeyore/linalg/__init__.py
eeyore/linalg/is_pos_def.py
eeyore/linalg/nearest_pd.py
eeyore/models/__init__.py
eeyore/models/bayesian_model.py
eeyore/models/distribution_model.py
eeyore/models/log_target_model.py
eeyore/models/logistic_regression.py
eeyore/models/mlp.py
eeyore/models/model.py
eeyore/models/tmp.py
eeyore/samplers/__init__.py
eeyore/samplers/am.py
eeyore/samplers/dmcl.py
eeyore/samplers/gibbs.py
eeyore/samplers/hmc.py
eeyore/samplers/mala.py
eeyore/samplers/metropolis_hastings.py
eeyore/samplers/multi_chain_serial_sampler.py
eeyore/samplers/power_posterior_sampler.py
eeyore/samplers/ram.py
eeyore/samplers/sampler.py
eeyore/samplers/serial_sampler.py
eeyore-0.0.20.dist-info/LICENSE.txt
eeyore-0.0.20.dist-info/METADATA
eeyore-0.0.20.dist-info/WHEEL
eeyore-0.0.20.dist-info/top_level.txt
eeyore-0.0.20.dist-info/RECORD
